{
  "title": "The Narrative Structure of Consciousness",
  "pattern": "philosophical_transformation",
  "character_info": "The main character is Philosophical Inquirer, a mentor.",
  "outline": [
    {
      "section": 1,
      "title": "Status Quo",
      "description": "In this section, the story addresses the 'Status Quo' stage of the philosophical_transformation pattern.",
      "key_elements": [
        "Element 1 for Status Quo",
        "Element 2 for Status Quo",
        "Element 3 for Status Quo"
      ]
    },
    {
      "section": 2,
      "title": "Disruption",
      "description": "In this section, the story addresses the 'Disruption' stage of the philosophical_transformation pattern.",
      "key_elements": [
        "Element 1 for Disruption",
        "Element 2 for Disruption",
        "Element 3 for Disruption"
      ]
    },
    {
      "section": 3,
      "title": "Resistance",
      "description": "In this section, the story addresses the 'Resistance' stage of the philosophical_transformation pattern.",
      "key_elements": [
        "Element 1 for Resistance",
        "Element 2 for Resistance",
        "Element 3 for Resistance"
      ]
    },
    {
      "section": 4,
      "title": "Struggle",
      "description": "In this section, the story addresses the 'Struggle' stage of the philosophical_transformation pattern.",
      "key_elements": [
        "Element 1 for Struggle",
        "Element 2 for Struggle",
        "Element 3 for Struggle"
      ]
    },
    {
      "section": 5,
      "title": "Discovery",
      "description": "In this section, the story addresses the 'Discovery' stage of the philosophical_transformation pattern.",
      "key_elements": [
        "Element 1 for Discovery",
        "Element 2 for Discovery",
        "Element 3 for Discovery"
      ]
    },
    {
      "section": 6,
      "title": "Integration",
      "description": "In this section, the story addresses the 'Integration' stage of the philosophical_transformation pattern.",
      "key_elements": [
        "Element 1 for Integration",
        "Element 2 for Integration",
        "Element 3 for Integration"
      ]
    },
    {
      "section": 7,
      "title": "New Normal",
      "description": "In this section, the story addresses the 'New Normal' stage of the philosophical_transformation pattern.",
      "key_elements": [
        "Element 1 for New Normal",
        "Element 2 for New Normal",
        "Element 3 for New Normal"
      ]
    },
    {
      "section": 8,
      "title": "The Ordinary World",
      "description": "In this section, the story addresses the 'The Ordinary World' stage of the philosophical_transformation pattern.",
      "key_elements": [
        "Element 1 for The Ordinary World",
        "Element 2 for The Ordinary World",
        "Element 3 for The Ordinary World"
      ]
    },
    {
      "section": 9,
      "title": "The Journey Begins",
      "description": "In this section, the story addresses the 'The Journey Begins' stage of the philosophical_transformation pattern.",
      "key_elements": [
        "Element 1 for The Journey Begins",
        "Element 2 for The Journey Begins",
        "Element 3 for The Journey Begins"
      ]
    },
    {
      "section": 10,
      "title": "The Strange New World",
      "description": "In this section, the story addresses the 'The Strange New World' stage of the philosophical_transformation pattern.",
      "key_elements": [
        "Element 1 for The Strange New World",
        "Element 2 for The Strange New World",
        "Element 3 for The Strange New World"
      ]
    },
    {
      "section": 11,
      "title": "The Return",
      "description": "In this section, the story addresses the 'The Return' stage of the philosophical_transformation pattern.",
      "key_elements": [
        "Element 1 for The Return",
        "Element 2 for The Return",
        "Element 3 for The Return"
      ]
    }
  ],
  "created_at": "2025-05-13T00:07:41.340887"
}