{
  "scene_title": "Beyond Categorical Thinking",
  "pattern_stage": "The Strange New World",
  "characters": [
    "Philosophical Inquirer"
  ],
  "setting": "A realm where the boundaries between epistemological frameworks dissolve, revealing the interdependence of seemingly contradictory philosophical systems",
  "goal": "The goal of this scene is to demonstrate the 'The Strange New World' stage",
  "conflict": "The conflict in this scene involves Philosophical Inquirer",
  "outcome": "The outcome of this scene moves the story forward by...",
  "notes": "This scene is a key moment in the The Strange New World stage of the story.",
  "created_at": "2025-05-13T00:07:58.070629"
}